enigma_enhanced/VERSION
enigma_enhanced/__init__.py
enigma_enhanced/engine.py
EnigmaEnhanced-0.2.4.dist-info/LICENSE
EnigmaEnhanced-0.2.4.dist-info/METADATA
EnigmaEnhanced-0.2.4.dist-info/WHEEL
EnigmaEnhanced-0.2.4.dist-info/entry_points.txt
EnigmaEnhanced-0.2.4.dist-info/top_level.txt
EnigmaEnhanced-0.2.4.dist-info/RECORD
