Metadata-Version: 2.1
Name: EnigmaEnhanced
Version: 0.2.4
Summary: A stateless enhanced Enigma cipher machine with full CLI support
Home-page: https://github.com/PaulLiszt/EnigmaEnhanced
Author: PaulLiszt
Author-email: paullizst@gmail.com
License: MIT
Project-URL: Source, https://github.com/PaulLiszt/EnigmaEnhanced
Project-URL: Bug Reports, https://github.com/PaulLiszt/EnigmaEnhanced/issues
Project-URL: Documentation, https://github.com/PaulLiszt/EnigmaEnhanced/blob/main/README.md
Keywords: enigma cipher cryptography security education
Classifier: Programming Language :: Python :: 3
Classifier: License :: OSI Approved :: MIT License
Classifier: Operating System :: OS Independent
Classifier: Development Status :: 4 - Beta
Classifier: Intended Audience :: Education
Classifier: Intended Audience :: Developers
Classifier: Topic :: Security :: Cryptography
Classifier: Topic :: Education
Requires-Python: >=3.6
License-File: LICENSE
